spectral_connectivity/__init__.py
spectral_connectivity/connectivity.py
spectral_connectivity/minimum_phase_decomposition.py
spectral_connectivity/simulate.py
spectral_connectivity/statistics.py
spectral_connectivity/transforms.py
spectral_connectivity/wrapper.py
tests/__init__.py
tests/test_connectivity.py
tests/test_minimum_phase_decomposition.py
tests/test_statistics.py
tests/test_transforms.py
tests/test_wrapper.py
spectral_connectivity-1.1.2.dist-info/LICENSE
spectral_connectivity-1.1.2.dist-info/METADATA
spectral_connectivity-1.1.2.dist-info/WHEEL
spectral_connectivity-1.1.2.dist-info/top_level.txt
spectral_connectivity-1.1.2.dist-info/RECORD
