Metadata-Version: 2.1
Name: spectral-connectivity
Version: 1.1.2
Summary: Frequency domain functional and directedconnectivity analysis tools for electrophysiologicaldata
Home-page: https://github.com/Eden-Kramer-Lab/spectral_connectivity
Author: Eric Denovellis
Author-email: eric.denovellis@ucsf.edu
License: GPL-3.0
Project-URL: Documentation, https://spectral-connectivity.readthedocs.io/en/latest/
Project-URL: Bug Reports, https://github.com/Eden-Kramer-Lab/spectral_connectivity/issues
Project-URL: Source, https://github.com/Eden-Kramer-Lab/spectral_connectivity
Keywords: python neuroscience electrophysiology multitaper spectrogram frequency-domain
Platform: any
Classifier: Intended Audience :: Science/Research
Classifier: License :: OSI Approved :: GNU General Public License v3 (GPLv3)
Classifier: Programming Language :: Python
Classifier: Topic :: Scientific/Engineering
Classifier: Operating System :: Microsoft :: Windows
Classifier: Operating System :: POSIX
Classifier: Operating System :: Unix
Classifier: Operating System :: MacOS
Classifier: Programming Language :: Python :: 3
Requires-Python: >=3
License-File: LICENSE
Requires-Dist: numpy (>=1.11)
Requires-Dist: scipy
Requires-Dist: xarray
Requires-Dist: matplotlib
